<?xml version="1.0" encoding="UTF-8"?>
<config xmlns="http://www.knime.org/2008/09/XMLConfig" xmlns:xsi="http://www.w3.org/2001/XMLSchema-instance" xsi:schemaLocation="http://www.knime.org/2008/09/XMLConfig http://www.knime.org/XMLConfig_2008_09.xsd" key="spec.xml">
<entry key="spec_name" type="xstring" value="default"/>
<entry key="number_columns" type="xint" value="63"/>
<config key="column_spec_0">
<entry key="column_name" type="xstring" value="mercado"/>
<config key="element_names">
<entry key="array-size" type="xint" value="0"/>
</config>
<config key="column_type">
<entry key="cell_class" type="xstring" value="org.knime.core.data.def.StringCell"/>
</config>
<config key="column_domain">
<config key="possible_values">
<entry key="array-size" type="xint" value="1"/>
<config key="0">
<entry key="datacell" type="xstring" value="org.knime.core.data.def.StringCell"/>
<config key="org.knime.core.data.def.StringCell">
<entry key="StringCell" type="xstring" value="NASDAQ"/>
</config>
</config>
</config>
</config>
<config key="column_properties"/>
</config>
<config key="column_spec_1">
<entry key="column_name" type="xstring" value="mercado_Count"/>
<config key="element_names">
<entry key="array-size" type="xint" value="0"/>
</config>
<config key="column_type">
<entry key="cell_class" type="xstring" value="org.knime.core.data.def.IntCell"/>
</config>
<config key="column_domain">
<config key="lower_bound">
<entry key="datacell" type="xstring" value="org.knime.core.data.def.IntCell"/>
<config key="org.knime.core.data.def.IntCell">
<entry key="IntCell" type="xint" value="30"/>
</config>
</config>
<config key="upper_bound">
<entry key="datacell" type="xstring" value="org.knime.core.data.def.IntCell"/>
<config key="org.knime.core.data.def.IntCell">
<entry key="IntCell" type="xint" value="30"/>
</config>
</config>
</config>
<config key="column_properties"/>
</config>
<config key="column_spec_2">
<entry key="column_name" type="xstring" value="Relative Frequency (mercado)"/>
<config key="element_names">
<entry key="array-size" type="xint" value="0"/>
</config>
<config key="column_type">
<entry key="cell_class" type="xstring" value="org.knime.core.data.def.DoubleCell"/>
</config>
<config key="column_domain">
<config key="lower_bound">
<entry key="datacell" type="xstring" value="org.knime.core.data.def.DoubleCell"/>
<config key="org.knime.core.data.def.DoubleCell">
<entry key="DoubleCell" type="xdouble" value="0.0"/>
</config>
</config>
<config key="upper_bound">
<entry key="datacell" type="xstring" value="org.knime.core.data.def.DoubleCell"/>
<config key="org.knime.core.data.def.DoubleCell">
<entry key="DoubleCell" type="xdouble" value="1.0"/>
</config>
</config>
</config>
<config key="column_properties"/>
</config>
<config key="column_spec_3">
<entry key="column_name" type="xstring" value="ticker"/>
<config key="element_names">
<entry key="array-size" type="xint" value="0"/>
</config>
<config key="column_type">
<entry key="cell_class" type="xstring" value="org.knime.core.data.def.StringCell"/>
</config>
<config key="column_domain">
<config key="possible_values">
<entry key="array-size" type="xint" value="1"/>
<config key="0">
<entry key="datacell" type="xstring" value="org.knime.core.data.def.StringCell"/>
<config key="org.knime.core.data.def.StringCell">
<entry key="StringCell" type="xstring" value="PT"/>
</config>
</config>
</config>
</config>
<config key="column_properties"/>
</config>
<config key="column_spec_4">
<entry key="column_name" type="xstring" value="ticker_Count"/>
<config key="element_names">
<entry key="array-size" type="xint" value="0"/>
</config>
<config key="column_type">
<entry key="cell_class" type="xstring" value="org.knime.core.data.def.IntCell"/>
</config>
<config key="column_domain">
<config key="lower_bound">
<entry key="datacell" type="xstring" value="org.knime.core.data.def.IntCell"/>
<config key="org.knime.core.data.def.IntCell">
<entry key="IntCell" type="xint" value="30"/>
</config>
</config>
<config key="upper_bound">
<entry key="datacell" type="xstring" value="org.knime.core.data.def.IntCell"/>
<config key="org.knime.core.data.def.IntCell">
<entry key="IntCell" type="xint" value="30"/>
</config>
</config>
</config>
<config key="column_properties"/>
</config>
<config key="column_spec_5">
<entry key="column_name" type="xstring" value="Relative Frequency (ticker)"/>
<config key="element_names">
<entry key="array-size" type="xint" value="0"/>
</config>
<config key="column_type">
<entry key="cell_class" type="xstring" value="org.knime.core.data.def.DoubleCell"/>
</config>
<config key="column_domain">
<config key="lower_bound">
<entry key="datacell" type="xstring" value="org.knime.core.data.def.DoubleCell"/>
<config key="org.knime.core.data.def.DoubleCell">
<entry key="DoubleCell" type="xdouble" value="0.0"/>
</config>
</config>
<config key="upper_bound">
<entry key="datacell" type="xstring" value="org.knime.core.data.def.DoubleCell"/>
<config key="org.knime.core.data.def.DoubleCell">
<entry key="DoubleCell" type="xdouble" value="1.0"/>
</config>
</config>
</config>
<config key="column_properties"/>
</config>
<config key="column_spec_6">
<entry key="column_name" type="xstring" value="instante"/>
<config key="element_names">
<entry key="array-size" type="xint" value="0"/>
</config>
<config key="column_type">
<entry key="cell_class" type="xstring" value="org.knime.core.data.def.DoubleCell"/>
</config>
<config key="column_domain">
<config key="lower_bound">
<entry key="datacell" type="xstring" value="org.knime.core.data.def.DoubleCell"/>
<config key="org.knime.core.data.def.DoubleCell">
<entry key="DoubleCell" type="xdouble" value="2.019112509E13"/>
</config>
</config>
<config key="upper_bound">
<entry key="datacell" type="xstring" value="org.knime.core.data.def.DoubleCell"/>
<config key="org.knime.core.data.def.DoubleCell">
<entry key="DoubleCell" type="xdouble" value="2.019112618E13"/>
</config>
</config>
</config>
<config key="column_properties"/>
</config>
<config key="column_spec_7">
<entry key="column_name" type="xstring" value="instante_Count"/>
<config key="element_names">
<entry key="array-size" type="xint" value="0"/>
</config>
<config key="column_type">
<entry key="cell_class" type="xstring" value="org.knime.core.data.def.IntCell"/>
</config>
<config key="column_domain">
<config key="lower_bound">
<entry key="datacell" type="xstring" value="org.knime.core.data.def.IntCell"/>
<config key="org.knime.core.data.def.IntCell">
<entry key="IntCell" type="xint" value="1"/>
</config>
</config>
<config key="upper_bound">
<entry key="datacell" type="xstring" value="org.knime.core.data.def.IntCell"/>
<config key="org.knime.core.data.def.IntCell">
<entry key="IntCell" type="xint" value="2"/>
</config>
</config>
</config>
<config key="column_properties"/>
</config>
<config key="column_spec_8">
<entry key="column_name" type="xstring" value="Relative Frequency (instante)"/>
<config key="element_names">
<entry key="array-size" type="xint" value="0"/>
</config>
<config key="column_type">
<entry key="cell_class" type="xstring" value="org.knime.core.data.def.DoubleCell"/>
</config>
<config key="column_domain">
<config key="lower_bound">
<entry key="datacell" type="xstring" value="org.knime.core.data.def.DoubleCell"/>
<config key="org.knime.core.data.def.DoubleCell">
<entry key="DoubleCell" type="xdouble" value="0.0"/>
</config>
</config>
<config key="upper_bound">
<entry key="datacell" type="xstring" value="org.knime.core.data.def.DoubleCell"/>
<config key="org.knime.core.data.def.DoubleCell">
<entry key="DoubleCell" type="xdouble" value="1.0"/>
</config>
</config>
</config>
<config key="column_properties"/>
</config>
<config key="column_spec_9">
<entry key="column_name" type="xstring" value="precio"/>
<config key="element_names">
<entry key="array-size" type="xint" value="0"/>
</config>
<config key="column_type">
<entry key="cell_class" type="xstring" value="org.knime.core.data.def.StringCell"/>
</config>
<config key="column_domain">
<config key="possible_values">
<entry key="array-size" type="xint" value="11"/>
<config key="0">
<entry key="datacell" type="xstring" value="org.knime.core.data.def.StringCell"/>
<config key="org.knime.core.data.def.StringCell">
<entry key="StringCell" type="xstring" value="0,45"/>
</config>
</config>
<config key="1">
<entry key="datacell" type="xstring" value="org.knime.core.data.def.StringCell"/>
<config key="org.knime.core.data.def.StringCell">
<entry key="StringCell" type="xstring" value="0,51"/>
</config>
</config>
<config key="2">
<entry key="datacell" type="xstring" value="org.knime.core.data.def.StringCell"/>
<config key="org.knime.core.data.def.StringCell">
<entry key="StringCell" type="xstring" value="0,7"/>
</config>
</config>
<config key="3">
<entry key="datacell" type="xstring" value="org.knime.core.data.def.StringCell"/>
<config key="org.knime.core.data.def.StringCell">
<entry key="StringCell" type="xstring" value="1,2"/>
</config>
</config>
<config key="4">
<entry key="datacell" type="xstring" value="org.knime.core.data.def.StringCell"/>
<config key="org.knime.core.data.def.StringCell">
<entry key="StringCell" type="xstring" value="1,5"/>
</config>
</config>
<config key="5">
<entry key="datacell" type="xstring" value="org.knime.core.data.def.StringCell"/>
<config key="org.knime.core.data.def.StringCell">
<entry key="StringCell" type="xstring" value="1,7"/>
</config>
</config>
<config key="6">
<entry key="datacell" type="xstring" value="org.knime.core.data.def.StringCell"/>
<config key="org.knime.core.data.def.StringCell">
<entry key="StringCell" type="xstring" value="2,1"/>
</config>
</config>
<config key="7">
<entry key="datacell" type="xstring" value="org.knime.core.data.def.StringCell"/>
<config key="org.knime.core.data.def.StringCell">
<entry key="StringCell" type="xstring" value="2"/>
</config>
</config>
<config key="8">
<entry key="datacell" type="xstring" value="org.knime.core.data.def.StringCell"/>
<config key="org.knime.core.data.def.StringCell">
<entry key="StringCell" type="xstring" value="1,9"/>
</config>
</config>
<config key="9">
<entry key="datacell" type="xstring" value="org.knime.core.data.def.StringCell"/>
<config key="org.knime.core.data.def.StringCell">
<entry key="StringCell" type="xstring" value="1,6"/>
</config>
</config>
<config key="10">
<entry key="datacell" type="xstring" value="org.knime.core.data.def.StringCell"/>
<config key="org.knime.core.data.def.StringCell">
<entry key="StringCell" type="xstring" value="0,2"/>
</config>
</config>
</config>
</config>
<config key="column_properties"/>
</config>
<config key="column_spec_10">
<entry key="column_name" type="xstring" value="precio_Count"/>
<config key="element_names">
<entry key="array-size" type="xint" value="0"/>
</config>
<config key="column_type">
<entry key="cell_class" type="xstring" value="org.knime.core.data.def.IntCell"/>
</config>
<config key="column_domain">
<config key="lower_bound">
<entry key="datacell" type="xstring" value="org.knime.core.data.def.IntCell"/>
<config key="org.knime.core.data.def.IntCell">
<entry key="IntCell" type="xint" value="1"/>
</config>
</config>
<config key="upper_bound">
<entry key="datacell" type="xstring" value="org.knime.core.data.def.IntCell"/>
<config key="org.knime.core.data.def.IntCell">
<entry key="IntCell" type="xint" value="13"/>
</config>
</config>
</config>
<config key="column_properties"/>
</config>
<config key="column_spec_11">
<entry key="column_name" type="xstring" value="Relative Frequency (precio)"/>
<config key="element_names">
<entry key="array-size" type="xint" value="0"/>
</config>
<config key="column_type">
<entry key="cell_class" type="xstring" value="org.knime.core.data.def.DoubleCell"/>
</config>
<config key="column_domain">
<config key="lower_bound">
<entry key="datacell" type="xstring" value="org.knime.core.data.def.DoubleCell"/>
<config key="org.knime.core.data.def.DoubleCell">
<entry key="DoubleCell" type="xdouble" value="0.0"/>
</config>
</config>
<config key="upper_bound">
<entry key="datacell" type="xstring" value="org.knime.core.data.def.DoubleCell"/>
<config key="org.knime.core.data.def.DoubleCell">
<entry key="DoubleCell" type="xdouble" value="1.0"/>
</config>
</config>
</config>
<config key="column_properties"/>
</config>
<config key="column_spec_12">
<entry key="column_name" type="xstring" value="volumen"/>
<config key="element_names">
<entry key="array-size" type="xint" value="0"/>
</config>
<config key="column_type">
<entry key="cell_class" type="xstring" value="org.knime.core.data.def.IntCell"/>
</config>
<config key="column_domain">
<config key="lower_bound">
<entry key="datacell" type="xstring" value="org.knime.core.data.def.IntCell"/>
<config key="org.knime.core.data.def.IntCell">
<entry key="IntCell" type="xint" value="20000"/>
</config>
</config>
<config key="upper_bound">
<entry key="datacell" type="xstring" value="org.knime.core.data.def.IntCell"/>
<config key="org.knime.core.data.def.IntCell">
<entry key="IntCell" type="xint" value="500000"/>
</config>
</config>
</config>
<config key="column_properties"/>
</config>
<config key="column_spec_13">
<entry key="column_name" type="xstring" value="volumen_Count"/>
<config key="element_names">
<entry key="array-size" type="xint" value="0"/>
</config>
<config key="column_type">
<entry key="cell_class" type="xstring" value="org.knime.core.data.def.IntCell"/>
</config>
<config key="column_domain">
<config key="lower_bound">
<entry key="datacell" type="xstring" value="org.knime.core.data.def.IntCell"/>
<config key="org.knime.core.data.def.IntCell">
<entry key="IntCell" type="xint" value="1"/>
</config>
</config>
<config key="upper_bound">
<entry key="datacell" type="xstring" value="org.knime.core.data.def.IntCell"/>
<config key="org.knime.core.data.def.IntCell">
<entry key="IntCell" type="xint" value="20"/>
</config>
</config>
</config>
<config key="column_properties"/>
</config>
<config key="column_spec_14">
<entry key="column_name" type="xstring" value="Relative Frequency (volumen)"/>
<config key="element_names">
<entry key="array-size" type="xint" value="0"/>
</config>
<config key="column_type">
<entry key="cell_class" type="xstring" value="org.knime.core.data.def.DoubleCell"/>
</config>
<config key="column_domain">
<config key="lower_bound">
<entry key="datacell" type="xstring" value="org.knime.core.data.def.DoubleCell"/>
<config key="org.knime.core.data.def.DoubleCell">
<entry key="DoubleCell" type="xdouble" value="0.0"/>
</config>
</config>
<config key="upper_bound">
<entry key="datacell" type="xstring" value="org.knime.core.data.def.DoubleCell"/>
<config key="org.knime.core.data.def.DoubleCell">
<entry key="DoubleCell" type="xdouble" value="1.0"/>
</config>
</config>
</config>
<config key="column_properties"/>
</config>
<config key="column_spec_15">
<entry key="column_name" type="xstring" value="anio"/>
<config key="element_names">
<entry key="array-size" type="xint" value="0"/>
</config>
<config key="column_type">
<entry key="cell_class" type="xstring" value="org.knime.core.data.def.IntCell"/>
</config>
<config key="column_domain">
<config key="lower_bound">
<entry key="datacell" type="xstring" value="org.knime.core.data.def.IntCell"/>
<config key="org.knime.core.data.def.IntCell">
<entry key="IntCell" type="xint" value="2019"/>
</config>
</config>
<config key="upper_bound">
<entry key="datacell" type="xstring" value="org.knime.core.data.def.IntCell"/>
<config key="org.knime.core.data.def.IntCell">
<entry key="IntCell" type="xint" value="2019"/>
</config>
</config>
</config>
<config key="column_properties"/>
</config>
<config key="column_spec_16">
<entry key="column_name" type="xstring" value="anio_Count"/>
<config key="element_names">
<entry key="array-size" type="xint" value="0"/>
</config>
<config key="column_type">
<entry key="cell_class" type="xstring" value="org.knime.core.data.def.IntCell"/>
</config>
<config key="column_domain">
<config key="lower_bound">
<entry key="datacell" type="xstring" value="org.knime.core.data.def.IntCell"/>
<config key="org.knime.core.data.def.IntCell">
<entry key="IntCell" type="xint" value="30"/>
</config>
</config>
<config key="upper_bound">
<entry key="datacell" type="xstring" value="org.knime.core.data.def.IntCell"/>
<config key="org.knime.core.data.def.IntCell">
<entry key="IntCell" type="xint" value="30"/>
</config>
</config>
</config>
<config key="column_properties"/>
</config>
<config key="column_spec_17">
<entry key="column_name" type="xstring" value="Relative Frequency (anio)"/>
<config key="element_names">
<entry key="array-size" type="xint" value="0"/>
</config>
<config key="column_type">
<entry key="cell_class" type="xstring" value="org.knime.core.data.def.DoubleCell"/>
</config>
<config key="column_domain">
<config key="lower_bound">
<entry key="datacell" type="xstring" value="org.knime.core.data.def.DoubleCell"/>
<config key="org.knime.core.data.def.DoubleCell">
<entry key="DoubleCell" type="xdouble" value="0.0"/>
</config>
</config>
<config key="upper_bound">
<entry key="datacell" type="xstring" value="org.knime.core.data.def.DoubleCell"/>
<config key="org.knime.core.data.def.DoubleCell">
<entry key="DoubleCell" type="xdouble" value="1.0"/>
</config>
</config>
</config>
<config key="column_properties"/>
</config>
<config key="column_spec_18">
<entry key="column_name" type="xstring" value="mes"/>
<config key="element_names">
<entry key="array-size" type="xint" value="0"/>
</config>
<config key="column_type">
<entry key="cell_class" type="xstring" value="org.knime.core.data.def.IntCell"/>
</config>
<config key="column_domain">
<config key="lower_bound">
<entry key="datacell" type="xstring" value="org.knime.core.data.def.IntCell"/>
<config key="org.knime.core.data.def.IntCell">
<entry key="IntCell" type="xint" value="11"/>
</config>
</config>
<config key="upper_bound">
<entry key="datacell" type="xstring" value="org.knime.core.data.def.IntCell"/>
<config key="org.knime.core.data.def.IntCell">
<entry key="IntCell" type="xint" value="11"/>
</config>
</config>
</config>
<config key="column_properties"/>
</config>
<config key="column_spec_19">
<entry key="column_name" type="xstring" value="mes_Count"/>
<config key="element_names">
<entry key="array-size" type="xint" value="0"/>
</config>
<config key="column_type">
<entry key="cell_class" type="xstring" value="org.knime.core.data.def.IntCell"/>
</config>
<config key="column_domain">
<config key="lower_bound">
<entry key="datacell" type="xstring" value="org.knime.core.data.def.IntCell"/>
<config key="org.knime.core.data.def.IntCell">
<entry key="IntCell" type="xint" value="30"/>
</config>
</config>
<config key="upper_bound">
<entry key="datacell" type="xstring" value="org.knime.core.data.def.IntCell"/>
<config key="org.knime.core.data.def.IntCell">
<entry key="IntCell" type="xint" value="30"/>
</config>
</config>
</config>
<config key="column_properties"/>
</config>
<config key="column_spec_20">
<entry key="column_name" type="xstring" value="Relative Frequency (mes)"/>
<config key="element_names">
<entry key="array-size" type="xint" value="0"/>
</config>
<config key="column_type">
<entry key="cell_class" type="xstring" value="org.knime.core.data.def.DoubleCell"/>
</config>
<config key="column_domain">
<config key="lower_bound">
<entry key="datacell" type="xstring" value="org.knime.core.data.def.DoubleCell"/>
<config key="org.knime.core.data.def.DoubleCell">
<entry key="DoubleCell" type="xdouble" value="0.0"/>
</config>
</config>
<config key="upper_bound">
<entry key="datacell" type="xstring" value="org.knime.core.data.def.DoubleCell"/>
<config key="org.knime.core.data.def.DoubleCell">
<entry key="DoubleCell" type="xdouble" value="1.0"/>
</config>
</config>
</config>
<config key="column_properties"/>
</config>
<config key="column_spec_21">
<entry key="column_name" type="xstring" value="dia"/>
<config key="element_names">
<entry key="array-size" type="xint" value="0"/>
</config>
<config key="column_type">
<entry key="cell_class" type="xstring" value="org.knime.core.data.def.IntCell"/>
</config>
<config key="column_domain">
<config key="lower_bound">
<entry key="datacell" type="xstring" value="org.knime.core.data.def.IntCell"/>
<config key="org.knime.core.data.def.IntCell">
<entry key="IntCell" type="xint" value="25"/>
</config>
</config>
<config key="upper_bound">
<entry key="datacell" type="xstring" value="org.knime.core.data.def.IntCell"/>
<config key="org.knime.core.data.def.IntCell">
<entry key="IntCell" type="xint" value="27"/>
</config>
</config>
</config>
<config key="column_properties"/>
</config>
<config key="column_spec_22">
<entry key="column_name" type="xstring" value="dia_Count"/>
<config key="element_names">
<entry key="array-size" type="xint" value="0"/>
</config>
<config key="column_type">
<entry key="cell_class" type="xstring" value="org.knime.core.data.def.IntCell"/>
</config>
<config key="column_domain">
<config key="lower_bound">
<entry key="datacell" type="xstring" value="org.knime.core.data.def.IntCell"/>
<config key="org.knime.core.data.def.IntCell">
<entry key="IntCell" type="xint" value="10"/>
</config>
</config>
<config key="upper_bound">
<entry key="datacell" type="xstring" value="org.knime.core.data.def.IntCell"/>
<config key="org.knime.core.data.def.IntCell">
<entry key="IntCell" type="xint" value="10"/>
</config>
</config>
</config>
<config key="column_properties"/>
</config>
<config key="column_spec_23">
<entry key="column_name" type="xstring" value="Relative Frequency (dia)"/>
<config key="element_names">
<entry key="array-size" type="xint" value="0"/>
</config>
<config key="column_type">
<entry key="cell_class" type="xstring" value="org.knime.core.data.def.DoubleCell"/>
</config>
<config key="column_domain">
<config key="lower_bound">
<entry key="datacell" type="xstring" value="org.knime.core.data.def.DoubleCell"/>
<config key="org.knime.core.data.def.DoubleCell">
<entry key="DoubleCell" type="xdouble" value="0.0"/>
</config>
</config>
<config key="upper_bound">
<entry key="datacell" type="xstring" value="org.knime.core.data.def.DoubleCell"/>
<config key="org.knime.core.data.def.DoubleCell">
<entry key="DoubleCell" type="xdouble" value="1.0"/>
</config>
</config>
</config>
<config key="column_properties"/>
</config>
<config key="column_spec_24">
<entry key="column_name" type="xstring" value="hora"/>
<config key="element_names">
<entry key="array-size" type="xint" value="0"/>
</config>
<config key="column_type">
<entry key="cell_class" type="xstring" value="org.knime.core.data.def.IntCell"/>
</config>
<config key="column_domain">
<config key="lower_bound">
<entry key="datacell" type="xstring" value="org.knime.core.data.def.IntCell"/>
<config key="org.knime.core.data.def.IntCell">
<entry key="IntCell" type="xint" value="9"/>
</config>
</config>
<config key="upper_bound">
<entry key="datacell" type="xstring" value="org.knime.core.data.def.IntCell"/>
<config key="org.knime.core.data.def.IntCell">
<entry key="IntCell" type="xint" value="18"/>
</config>
</config>
</config>
<config key="column_properties"/>
</config>
<config key="column_spec_25">
<entry key="column_name" type="xstring" value="hora_Count"/>
<config key="element_names">
<entry key="array-size" type="xint" value="0"/>
</config>
<config key="column_type">
<entry key="cell_class" type="xstring" value="org.knime.core.data.def.IntCell"/>
</config>
<config key="column_domain">
<config key="lower_bound">
<entry key="datacell" type="xstring" value="org.knime.core.data.def.IntCell"/>
<config key="org.knime.core.data.def.IntCell">
<entry key="IntCell" type="xint" value="3"/>
</config>
</config>
<config key="upper_bound">
<entry key="datacell" type="xstring" value="org.knime.core.data.def.IntCell"/>
<config key="org.knime.core.data.def.IntCell">
<entry key="IntCell" type="xint" value="3"/>
</config>
</config>
</config>
<config key="column_properties"/>
</config>
<config key="column_spec_26">
<entry key="column_name" type="xstring" value="Relative Frequency (hora)"/>
<config key="element_names">
<entry key="array-size" type="xint" value="0"/>
</config>
<config key="column_type">
<entry key="cell_class" type="xstring" value="org.knime.core.data.def.DoubleCell"/>
</config>
<config key="column_domain">
<config key="lower_bound">
<entry key="datacell" type="xstring" value="org.knime.core.data.def.DoubleCell"/>
<config key="org.knime.core.data.def.DoubleCell">
<entry key="DoubleCell" type="xdouble" value="0.0"/>
</config>
</config>
<config key="upper_bound">
<entry key="datacell" type="xstring" value="org.knime.core.data.def.DoubleCell"/>
<config key="org.knime.core.data.def.DoubleCell">
<entry key="DoubleCell" type="xdouble" value="1.0"/>
</config>
</config>
</config>
<config key="column_properties"/>
</config>
<config key="column_spec_27">
<entry key="column_name" type="xstring" value="minuto"/>
<config key="element_names">
<entry key="array-size" type="xint" value="0"/>
</config>
<config key="column_type">
<entry key="cell_class" type="xstring" value="org.knime.core.data.def.IntCell"/>
</config>
<config key="column_domain">
<config key="lower_bound">
<entry key="datacell" type="xstring" value="org.knime.core.data.def.IntCell"/>
<config key="org.knime.core.data.def.IntCell">
<entry key="IntCell" type="xint" value="0"/>
</config>
</config>
<config key="upper_bound">
<entry key="datacell" type="xstring" value="org.knime.core.data.def.IntCell"/>
<config key="org.knime.core.data.def.IntCell">
<entry key="IntCell" type="xint" value="0"/>
</config>
</config>
</config>
<config key="column_properties"/>
</config>
<config key="column_spec_28">
<entry key="column_name" type="xstring" value="minuto_Count"/>
<config key="element_names">
<entry key="array-size" type="xint" value="0"/>
</config>
<config key="column_type">
<entry key="cell_class" type="xstring" value="org.knime.core.data.def.IntCell"/>
</config>
<config key="column_domain">
<config key="lower_bound">
<entry key="datacell" type="xstring" value="org.knime.core.data.def.IntCell"/>
<config key="org.knime.core.data.def.IntCell">
<entry key="IntCell" type="xint" value="30"/>
</config>
</config>
<config key="upper_bound">
<entry key="datacell" type="xstring" value="org.knime.core.data.def.IntCell"/>
<config key="org.knime.core.data.def.IntCell">
<entry key="IntCell" type="xint" value="30"/>
</config>
</config>
</config>
<config key="column_properties"/>
</config>
<config key="column_spec_29">
<entry key="column_name" type="xstring" value="Relative Frequency (minuto)"/>
<config key="element_names">
<entry key="array-size" type="xint" value="0"/>
</config>
<config key="column_type">
<entry key="cell_class" type="xstring" value="org.knime.core.data.def.DoubleCell"/>
</config>
<config key="column_domain">
<config key="lower_bound">
<entry key="datacell" type="xstring" value="org.knime.core.data.def.DoubleCell"/>
<config key="org.knime.core.data.def.DoubleCell">
<entry key="DoubleCell" type="xdouble" value="0.0"/>
</config>
</config>
<config key="upper_bound">
<entry key="datacell" type="xstring" value="org.knime.core.data.def.DoubleCell"/>
<config key="org.knime.core.data.def.DoubleCell">
<entry key="DoubleCell" type="xdouble" value="1.0"/>
</config>
</config>
</config>
<config key="column_properties"/>
</config>
<config key="column_spec_30">
<entry key="column_name" type="xstring" value="num vela ordenada"/>
<config key="element_names">
<entry key="array-size" type="xint" value="0"/>
</config>
<config key="column_type">
<entry key="cell_class" type="xstring" value="org.knime.core.data.def.IntCell"/>
</config>
<config key="column_domain">
<config key="lower_bound">
<entry key="datacell" type="xstring" value="org.knime.core.data.def.IntCell"/>
<config key="org.knime.core.data.def.IntCell">
<entry key="IntCell" type="xint" value="1"/>
</config>
</config>
<config key="upper_bound">
<entry key="datacell" type="xstring" value="org.knime.core.data.def.IntCell"/>
<config key="org.knime.core.data.def.IntCell">
<entry key="IntCell" type="xint" value="30"/>
</config>
</config>
</config>
<config key="column_properties"/>
</config>
<config key="column_spec_31">
<entry key="column_name" type="xstring" value="num vela ordenada_Count"/>
<config key="element_names">
<entry key="array-size" type="xint" value="0"/>
</config>
<config key="column_type">
<entry key="cell_class" type="xstring" value="org.knime.core.data.def.IntCell"/>
</config>
<config key="column_domain">
<config key="lower_bound">
<entry key="datacell" type="xstring" value="org.knime.core.data.def.IntCell"/>
<config key="org.knime.core.data.def.IntCell">
<entry key="IntCell" type="xint" value="1"/>
</config>
</config>
<config key="upper_bound">
<entry key="datacell" type="xstring" value="org.knime.core.data.def.IntCell"/>
<config key="org.knime.core.data.def.IntCell">
<entry key="IntCell" type="xint" value="1"/>
</config>
</config>
</config>
<config key="column_properties"/>
</config>
<config key="column_spec_32">
<entry key="column_name" type="xstring" value="Relative Frequency (num vela ordenada)"/>
<config key="element_names">
<entry key="array-size" type="xint" value="0"/>
</config>
<config key="column_type">
<entry key="cell_class" type="xstring" value="org.knime.core.data.def.DoubleCell"/>
</config>
<config key="column_domain">
<config key="lower_bound">
<entry key="datacell" type="xstring" value="org.knime.core.data.def.DoubleCell"/>
<config key="org.knime.core.data.def.DoubleCell">
<entry key="DoubleCell" type="xdouble" value="0.0"/>
</config>
</config>
<config key="upper_bound">
<entry key="datacell" type="xstring" value="org.knime.core.data.def.DoubleCell"/>
<config key="org.knime.core.data.def.DoubleCell">
<entry key="DoubleCell" type="xdouble" value="1.0"/>
</config>
</config>
</config>
<config key="column_properties"/>
</config>
<config key="column_spec_33">
<entry key="column_name" type="xstring" value="precio 1dias atras"/>
<config key="element_names">
<entry key="array-size" type="xint" value="0"/>
</config>
<config key="column_type">
<entry key="cell_class" type="xstring" value="org.knime.core.data.def.StringCell"/>
</config>
<config key="column_domain">
<config key="possible_values">
<entry key="array-size" type="xint" value="9"/>
<config key="0">
<entry key="datacell" type="xstring" value="org.knime.core.data.def.StringCell"/>
<config key="org.knime.core.data.def.StringCell">
<entry key="StringCell" type="xstring" value="0,45"/>
</config>
</config>
<config key="1">
<entry key="datacell" type="xstring" value="org.knime.core.data.def.StringCell"/>
<config key="org.knime.core.data.def.StringCell">
<entry key="StringCell" type="xstring" value="0,51"/>
</config>
</config>
<config key="2">
<entry key="datacell" type="xstring" value="org.knime.core.data.def.StringCell"/>
<config key="org.knime.core.data.def.StringCell">
<entry key="StringCell" type="xstring" value="0,7"/>
</config>
</config>
<config key="3">
<entry key="datacell" type="xstring" value="org.knime.core.data.def.StringCell"/>
<config key="org.knime.core.data.def.StringCell">
<entry key="StringCell" type="xstring" value="1,2"/>
</config>
</config>
<config key="4">
<entry key="datacell" type="xstring" value="org.knime.core.data.def.StringCell"/>
<config key="org.knime.core.data.def.StringCell">
<entry key="StringCell" type="xstring" value="1,5"/>
</config>
</config>
<config key="5">
<entry key="datacell" type="xstring" value="org.knime.core.data.def.StringCell"/>
<config key="org.knime.core.data.def.StringCell">
<entry key="StringCell" type="xstring" value="1,7"/>
</config>
</config>
<config key="6">
<entry key="datacell" type="xstring" value="org.knime.core.data.def.StringCell"/>
<config key="org.knime.core.data.def.StringCell">
<entry key="StringCell" type="xstring" value="2,1"/>
</config>
</config>
<config key="7">
<entry key="datacell" type="xstring" value="org.knime.core.data.def.StringCell"/>
<config key="org.knime.core.data.def.StringCell">
<entry key="StringCell" type="xstring" value="2"/>
</config>
</config>
<config key="8">
<entry key="datacell" type="xstring" value="org.knime.core.data.def.StringCell"/>
<config key="org.knime.core.data.def.StringCell">
<entry key="StringCell" type="xstring" value="1,9"/>
</config>
</config>
</config>
</config>
<config key="column_properties"/>
</config>
<config key="column_spec_34">
<entry key="column_name" type="xstring" value="precio 1dias atras_Count"/>
<config key="element_names">
<entry key="array-size" type="xint" value="0"/>
</config>
<config key="column_type">
<entry key="cell_class" type="xstring" value="org.knime.core.data.def.IntCell"/>
</config>
<config key="column_domain">
<config key="lower_bound">
<entry key="datacell" type="xstring" value="org.knime.core.data.def.IntCell"/>
<config key="org.knime.core.data.def.IntCell">
<entry key="IntCell" type="xint" value="1"/>
</config>
</config>
<config key="upper_bound">
<entry key="datacell" type="xstring" value="org.knime.core.data.def.IntCell"/>
<config key="org.knime.core.data.def.IntCell">
<entry key="IntCell" type="xint" value="22"/>
</config>
</config>
</config>
<config key="column_properties"/>
</config>
<config key="column_spec_35">
<entry key="column_name" type="xstring" value="Relative Frequency (precio 1dias atras)"/>
<config key="element_names">
<entry key="array-size" type="xint" value="0"/>
</config>
<config key="column_type">
<entry key="cell_class" type="xstring" value="org.knime.core.data.def.DoubleCell"/>
</config>
<config key="column_domain">
<config key="lower_bound">
<entry key="datacell" type="xstring" value="org.knime.core.data.def.DoubleCell"/>
<config key="org.knime.core.data.def.DoubleCell">
<entry key="DoubleCell" type="xdouble" value="0.0"/>
</config>
</config>
<config key="upper_bound">
<entry key="datacell" type="xstring" value="org.knime.core.data.def.DoubleCell"/>
<config key="org.knime.core.data.def.DoubleCell">
<entry key="DoubleCell" type="xdouble" value="1.0"/>
</config>
</config>
</config>
<config key="column_properties"/>
</config>
<config key="column_spec_36">
<entry key="column_name" type="xstring" value="precio 2dias atras"/>
<config key="element_names">
<entry key="array-size" type="xint" value="0"/>
</config>
<config key="column_type">
<entry key="cell_class" type="xstring" value="org.knime.core.data.def.StringCell"/>
</config>
<config key="column_domain">
<config key="possible_values">
<entry key="array-size" type="xint" value="1"/>
<config key="0">
<entry key="datacell" type="xstring" value="org.knime.core.data.def.StringCell"/>
<config key="org.knime.core.data.def.StringCell">
<entry key="StringCell" type="xstring" value="0,45"/>
</config>
</config>
</config>
</config>
<config key="column_properties"/>
</config>
<config key="column_spec_37">
<entry key="column_name" type="xstring" value="precio 2dias atras_Count"/>
<config key="element_names">
<entry key="array-size" type="xint" value="0"/>
</config>
<config key="column_type">
<entry key="cell_class" type="xstring" value="org.knime.core.data.def.IntCell"/>
</config>
<config key="column_domain">
<config key="lower_bound">
<entry key="datacell" type="xstring" value="org.knime.core.data.def.IntCell"/>
<config key="org.knime.core.data.def.IntCell">
<entry key="IntCell" type="xint" value="30"/>
</config>
</config>
<config key="upper_bound">
<entry key="datacell" type="xstring" value="org.knime.core.data.def.IntCell"/>
<config key="org.knime.core.data.def.IntCell">
<entry key="IntCell" type="xint" value="30"/>
</config>
</config>
</config>
<config key="column_properties"/>
</config>
<config key="column_spec_38">
<entry key="column_name" type="xstring" value="Relative Frequency (precio 2dias atras)"/>
<config key="element_names">
<entry key="array-size" type="xint" value="0"/>
</config>
<config key="column_type">
<entry key="cell_class" type="xstring" value="org.knime.core.data.def.DoubleCell"/>
</config>
<config key="column_domain">
<config key="lower_bound">
<entry key="datacell" type="xstring" value="org.knime.core.data.def.DoubleCell"/>
<config key="org.knime.core.data.def.DoubleCell">
<entry key="DoubleCell" type="xdouble" value="0.0"/>
</config>
</config>
<config key="upper_bound">
<entry key="datacell" type="xstring" value="org.knime.core.data.def.DoubleCell"/>
<config key="org.knime.core.data.def.DoubleCell">
<entry key="DoubleCell" type="xdouble" value="1.0"/>
</config>
</config>
</config>
<config key="column_properties"/>
</config>
<config key="column_spec_39">
<entry key="column_name" type="xstring" value="precio 3dias atras"/>
<config key="element_names">
<entry key="array-size" type="xint" value="0"/>
</config>
<config key="column_type">
<entry key="cell_class" type="xstring" value="org.knime.core.data.def.StringCell"/>
</config>
<config key="column_domain">
<config key="possible_values">
<entry key="array-size" type="xint" value="1"/>
<config key="0">
<entry key="datacell" type="xstring" value="org.knime.core.data.def.StringCell"/>
<config key="org.knime.core.data.def.StringCell">
<entry key="StringCell" type="xstring" value="0,45"/>
</config>
</config>
</config>
</config>
<config key="column_properties"/>
</config>
<config key="column_spec_40">
<entry key="column_name" type="xstring" value="precio 3dias atras_Count"/>
<config key="element_names">
<entry key="array-size" type="xint" value="0"/>
</config>
<config key="column_type">
<entry key="cell_class" type="xstring" value="org.knime.core.data.def.IntCell"/>
</config>
<config key="column_domain">
<config key="lower_bound">
<entry key="datacell" type="xstring" value="org.knime.core.data.def.IntCell"/>
<config key="org.knime.core.data.def.IntCell">
<entry key="IntCell" type="xint" value="30"/>
</config>
</config>
<config key="upper_bound">
<entry key="datacell" type="xstring" value="org.knime.core.data.def.IntCell"/>
<config key="org.knime.core.data.def.IntCell">
<entry key="IntCell" type="xint" value="30"/>
</config>
</config>
</config>
<config key="column_properties"/>
</config>
<config key="column_spec_41">
<entry key="column_name" type="xstring" value="Relative Frequency (precio 3dias atras)"/>
<config key="element_names">
<entry key="array-size" type="xint" value="0"/>
</config>
<config key="column_type">
<entry key="cell_class" type="xstring" value="org.knime.core.data.def.DoubleCell"/>
</config>
<config key="column_domain">
<config key="lower_bound">
<entry key="datacell" type="xstring" value="org.knime.core.data.def.DoubleCell"/>
<config key="org.knime.core.data.def.DoubleCell">
<entry key="DoubleCell" type="xdouble" value="0.0"/>
</config>
</config>
<config key="upper_bound">
<entry key="datacell" type="xstring" value="org.knime.core.data.def.DoubleCell"/>
<config key="org.knime.core.data.def.DoubleCell">
<entry key="DoubleCell" type="xdouble" value="1.0"/>
</config>
</config>
</config>
<config key="column_properties"/>
</config>
<config key="column_spec_42">
<entry key="column_name" type="xstring" value="precio 7dias atras"/>
<config key="element_names">
<entry key="array-size" type="xint" value="0"/>
</config>
<config key="column_type">
<entry key="cell_class" type="xstring" value="org.knime.core.data.def.StringCell"/>
</config>
<config key="column_domain">
<config key="possible_values">
<entry key="array-size" type="xint" value="1"/>
<config key="0">
<entry key="datacell" type="xstring" value="org.knime.core.data.def.StringCell"/>
<config key="org.knime.core.data.def.StringCell">
<entry key="StringCell" type="xstring" value="0,45"/>
</config>
</config>
</config>
</config>
<config key="column_properties"/>
</config>
<config key="column_spec_43">
<entry key="column_name" type="xstring" value="precio 7dias atras_Count"/>
<config key="element_names">
<entry key="array-size" type="xint" value="0"/>
</config>
<config key="column_type">
<entry key="cell_class" type="xstring" value="org.knime.core.data.def.IntCell"/>
</config>
<config key="column_domain">
<config key="lower_bound">
<entry key="datacell" type="xstring" value="org.knime.core.data.def.IntCell"/>
<config key="org.knime.core.data.def.IntCell">
<entry key="IntCell" type="xint" value="30"/>
</config>
</config>
<config key="upper_bound">
<entry key="datacell" type="xstring" value="org.knime.core.data.def.IntCell"/>
<config key="org.knime.core.data.def.IntCell">
<entry key="IntCell" type="xint" value="30"/>
</config>
</config>
</config>
<config key="column_properties"/>
</config>
<config key="column_spec_44">
<entry key="column_name" type="xstring" value="Relative Frequency (precio 7dias atras)"/>
<config key="element_names">
<entry key="array-size" type="xint" value="0"/>
</config>
<config key="column_type">
<entry key="cell_class" type="xstring" value="org.knime.core.data.def.DoubleCell"/>
</config>
<config key="column_domain">
<config key="lower_bound">
<entry key="datacell" type="xstring" value="org.knime.core.data.def.DoubleCell"/>
<config key="org.knime.core.data.def.DoubleCell">
<entry key="DoubleCell" type="xdouble" value="0.0"/>
</config>
</config>
<config key="upper_bound">
<entry key="datacell" type="xstring" value="org.knime.core.data.def.DoubleCell"/>
<config key="org.knime.core.data.def.DoubleCell">
<entry key="DoubleCell" type="xdouble" value="1.0"/>
</config>
</config>
</config>
<config key="column_properties"/>
</config>
<config key="column_spec_45">
<entry key="column_name" type="xstring" value="volumen 1dias atras"/>
<config key="element_names">
<entry key="array-size" type="xint" value="0"/>
</config>
<config key="column_type">
<entry key="cell_class" type="xstring" value="org.knime.core.data.def.IntCell"/>
</config>
<config key="column_domain">
<config key="lower_bound">
<entry key="datacell" type="xstring" value="org.knime.core.data.def.IntCell"/>
<config key="org.knime.core.data.def.IntCell">
<entry key="IntCell" type="xint" value="20000"/>
</config>
</config>
<config key="upper_bound">
<entry key="datacell" type="xstring" value="org.knime.core.data.def.IntCell"/>
<config key="org.knime.core.data.def.IntCell">
<entry key="IntCell" type="xint" value="500000"/>
</config>
</config>
</config>
<config key="column_properties"/>
</config>
<config key="column_spec_46">
<entry key="column_name" type="xstring" value="volumen 1dias atras_Count"/>
<config key="element_names">
<entry key="array-size" type="xint" value="0"/>
</config>
<config key="column_type">
<entry key="cell_class" type="xstring" value="org.knime.core.data.def.IntCell"/>
</config>
<config key="column_domain">
<config key="lower_bound">
<entry key="datacell" type="xstring" value="org.knime.core.data.def.IntCell"/>
<config key="org.knime.core.data.def.IntCell">
<entry key="IntCell" type="xint" value="1"/>
</config>
</config>
<config key="upper_bound">
<entry key="datacell" type="xstring" value="org.knime.core.data.def.IntCell"/>
<config key="org.knime.core.data.def.IntCell">
<entry key="IntCell" type="xint" value="22"/>
</config>
</config>
</config>
<config key="column_properties"/>
</config>
<config key="column_spec_47">
<entry key="column_name" type="xstring" value="Relative Frequency (volumen 1dias atras)"/>
<config key="element_names">
<entry key="array-size" type="xint" value="0"/>
</config>
<config key="column_type">
<entry key="cell_class" type="xstring" value="org.knime.core.data.def.DoubleCell"/>
</config>
<config key="column_domain">
<config key="lower_bound">
<entry key="datacell" type="xstring" value="org.knime.core.data.def.DoubleCell"/>
<config key="org.knime.core.data.def.DoubleCell">
<entry key="DoubleCell" type="xdouble" value="0.0"/>
</config>
</config>
<config key="upper_bound">
<entry key="datacell" type="xstring" value="org.knime.core.data.def.DoubleCell"/>
<config key="org.knime.core.data.def.DoubleCell">
<entry key="DoubleCell" type="xdouble" value="1.0"/>
</config>
</config>
</config>
<config key="column_properties"/>
</config>
<config key="column_spec_48">
<entry key="column_name" type="xstring" value="volumen 2dias atras"/>
<config key="element_names">
<entry key="array-size" type="xint" value="0"/>
</config>
<config key="column_type">
<entry key="cell_class" type="xstring" value="org.knime.core.data.def.IntCell"/>
</config>
<config key="column_domain">
<config key="lower_bound">
<entry key="datacell" type="xstring" value="org.knime.core.data.def.IntCell"/>
<config key="org.knime.core.data.def.IntCell">
<entry key="IntCell" type="xint" value="20000"/>
</config>
</config>
<config key="upper_bound">
<entry key="datacell" type="xstring" value="org.knime.core.data.def.IntCell"/>
<config key="org.knime.core.data.def.IntCell">
<entry key="IntCell" type="xint" value="20000"/>
</config>
</config>
</config>
<config key="column_properties"/>
</config>
<config key="column_spec_49">
<entry key="column_name" type="xstring" value="volumen 2dias atras_Count"/>
<config key="element_names">
<entry key="array-size" type="xint" value="0"/>
</config>
<config key="column_type">
<entry key="cell_class" type="xstring" value="org.knime.core.data.def.IntCell"/>
</config>
<config key="column_domain">
<config key="lower_bound">
<entry key="datacell" type="xstring" value="org.knime.core.data.def.IntCell"/>
<config key="org.knime.core.data.def.IntCell">
<entry key="IntCell" type="xint" value="30"/>
</config>
</config>
<config key="upper_bound">
<entry key="datacell" type="xstring" value="org.knime.core.data.def.IntCell"/>
<config key="org.knime.core.data.def.IntCell">
<entry key="IntCell" type="xint" value="30"/>
</config>
</config>
</config>
<config key="column_properties"/>
</config>
<config key="column_spec_50">
<entry key="column_name" type="xstring" value="Relative Frequency (volumen 2dias atras)"/>
<config key="element_names">
<entry key="array-size" type="xint" value="0"/>
</config>
<config key="column_type">
<entry key="cell_class" type="xstring" value="org.knime.core.data.def.DoubleCell"/>
</config>
<config key="column_domain">
<config key="lower_bound">
<entry key="datacell" type="xstring" value="org.knime.core.data.def.DoubleCell"/>
<config key="org.knime.core.data.def.DoubleCell">
<entry key="DoubleCell" type="xdouble" value="0.0"/>
</config>
</config>
<config key="upper_bound">
<entry key="datacell" type="xstring" value="org.knime.core.data.def.DoubleCell"/>
<config key="org.knime.core.data.def.DoubleCell">
<entry key="DoubleCell" type="xdouble" value="1.0"/>
</config>
</config>
</config>
<config key="column_properties"/>
</config>
<config key="column_spec_51">
<entry key="column_name" type="xstring" value="volumen 3dias atras"/>
<config key="element_names">
<entry key="array-size" type="xint" value="0"/>
</config>
<config key="column_type">
<entry key="cell_class" type="xstring" value="org.knime.core.data.def.IntCell"/>
</config>
<config key="column_domain">
<config key="lower_bound">
<entry key="datacell" type="xstring" value="org.knime.core.data.def.IntCell"/>
<config key="org.knime.core.data.def.IntCell">
<entry key="IntCell" type="xint" value="20000"/>
</config>
</config>
<config key="upper_bound">
<entry key="datacell" type="xstring" value="org.knime.core.data.def.IntCell"/>
<config key="org.knime.core.data.def.IntCell">
<entry key="IntCell" type="xint" value="20000"/>
</config>
</config>
</config>
<config key="column_properties"/>
</config>
<config key="column_spec_52">
<entry key="column_name" type="xstring" value="volumen 3dias atras_Count"/>
<config key="element_names">
<entry key="array-size" type="xint" value="0"/>
</config>
<config key="column_type">
<entry key="cell_class" type="xstring" value="org.knime.core.data.def.IntCell"/>
</config>
<config key="column_domain">
<config key="lower_bound">
<entry key="datacell" type="xstring" value="org.knime.core.data.def.IntCell"/>
<config key="org.knime.core.data.def.IntCell">
<entry key="IntCell" type="xint" value="30"/>
</config>
</config>
<config key="upper_bound">
<entry key="datacell" type="xstring" value="org.knime.core.data.def.IntCell"/>
<config key="org.knime.core.data.def.IntCell">
<entry key="IntCell" type="xint" value="30"/>
</config>
</config>
</config>
<config key="column_properties"/>
</config>
<config key="column_spec_53">
<entry key="column_name" type="xstring" value="Relative Frequency (volumen 3dias atras)"/>
<config key="element_names">
<entry key="array-size" type="xint" value="0"/>
</config>
<config key="column_type">
<entry key="cell_class" type="xstring" value="org.knime.core.data.def.DoubleCell"/>
</config>
<config key="column_domain">
<config key="lower_bound">
<entry key="datacell" type="xstring" value="org.knime.core.data.def.DoubleCell"/>
<config key="org.knime.core.data.def.DoubleCell">
<entry key="DoubleCell" type="xdouble" value="0.0"/>
</config>
</config>
<config key="upper_bound">
<entry key="datacell" type="xstring" value="org.knime.core.data.def.DoubleCell"/>
<config key="org.knime.core.data.def.DoubleCell">
<entry key="DoubleCell" type="xdouble" value="1.0"/>
</config>
</config>
</config>
<config key="column_properties"/>
</config>
<config key="column_spec_54">
<entry key="column_name" type="xstring" value="volumen 7dias atras"/>
<config key="element_names">
<entry key="array-size" type="xint" value="0"/>
</config>
<config key="column_type">
<entry key="cell_class" type="xstring" value="org.knime.core.data.def.IntCell"/>
</config>
<config key="column_domain">
<config key="lower_bound">
<entry key="datacell" type="xstring" value="org.knime.core.data.def.IntCell"/>
<config key="org.knime.core.data.def.IntCell">
<entry key="IntCell" type="xint" value="20000"/>
</config>
</config>
<config key="upper_bound">
<entry key="datacell" type="xstring" value="org.knime.core.data.def.IntCell"/>
<config key="org.knime.core.data.def.IntCell">
<entry key="IntCell" type="xint" value="20000"/>
</config>
</config>
</config>
<config key="column_properties"/>
</config>
<config key="column_spec_55">
<entry key="column_name" type="xstring" value="volumen 7dias atras_Count"/>
<config key="element_names">
<entry key="array-size" type="xint" value="0"/>
</config>
<config key="column_type">
<entry key="cell_class" type="xstring" value="org.knime.core.data.def.IntCell"/>
</config>
<config key="column_domain">
<config key="lower_bound">
<entry key="datacell" type="xstring" value="org.knime.core.data.def.IntCell"/>
<config key="org.knime.core.data.def.IntCell">
<entry key="IntCell" type="xint" value="30"/>
</config>
</config>
<config key="upper_bound">
<entry key="datacell" type="xstring" value="org.knime.core.data.def.IntCell"/>
<config key="org.knime.core.data.def.IntCell">
<entry key="IntCell" type="xint" value="30"/>
</config>
</config>
</config>
<config key="column_properties"/>
</config>
<config key="column_spec_56">
<entry key="column_name" type="xstring" value="Relative Frequency (volumen 7dias atras)"/>
<config key="element_names">
<entry key="array-size" type="xint" value="0"/>
</config>
<config key="column_type">
<entry key="cell_class" type="xstring" value="org.knime.core.data.def.DoubleCell"/>
</config>
<config key="column_domain">
<config key="lower_bound">
<entry key="datacell" type="xstring" value="org.knime.core.data.def.DoubleCell"/>
<config key="org.knime.core.data.def.DoubleCell">
<entry key="DoubleCell" type="xdouble" value="0.0"/>
</config>
</config>
<config key="upper_bound">
<entry key="datacell" type="xstring" value="org.knime.core.data.def.DoubleCell"/>
<config key="org.knime.core.data.def.DoubleCell">
<entry key="DoubleCell" type="xdouble" value="1.0"/>
</config>
</config>
</config>
<config key="column_properties"/>
</config>
<config key="column_spec_57">
<entry key="column_name" type="xstring" value="preciosubemas20pct que2diasatras"/>
<config key="element_names">
<entry key="array-size" type="xint" value="0"/>
</config>
<config key="column_type">
<entry key="cell_class" type="xstring" value="org.knime.core.data.def.StringCell"/>
</config>
<config key="column_domain">
<config key="possible_values">
<entry key="array-size" type="xint" value="4"/>
<config key="0">
<entry key="datacell" type="xstring" value="org.knime.core.data.def.StringCell"/>
<config key="org.knime.core.data.def.StringCell">
<entry key="StringCell" type="xstring" value="#REF!"/>
</config>
</config>
<config key="1">
<entry key="datacell" type="xstring" value="org.knime.core.data.def.StringCell"/>
<config key="org.knime.core.data.def.StringCell">
<entry key="StringCell" type="xstring" value="#VALUE!"/>
</config>
</config>
<config key="2">
<entry key="datacell" type="xstring" value="org.knime.core.data.def.StringCell"/>
<config key="org.knime.core.data.def.StringCell">
<entry key="StringCell" type="xstring" value="TRUE"/>
</config>
</config>
<config key="3">
<entry key="datacell" type="xstring" value="org.knime.core.data.def.StringCell"/>
<config key="org.knime.core.data.def.StringCell">
<entry key="StringCell" type="xstring" value="FALSE"/>
</config>
</config>
</config>
</config>
<config key="column_properties"/>
</config>
<config key="column_spec_58">
<entry key="column_name" type="xstring" value="preciosubemas20pct que2diasatras_Count"/>
<config key="element_names">
<entry key="array-size" type="xint" value="0"/>
</config>
<config key="column_type">
<entry key="cell_class" type="xstring" value="org.knime.core.data.def.IntCell"/>
</config>
<config key="column_domain">
<config key="lower_bound">
<entry key="datacell" type="xstring" value="org.knime.core.data.def.IntCell"/>
<config key="org.knime.core.data.def.IntCell">
<entry key="IntCell" type="xint" value="1"/>
</config>
</config>
<config key="upper_bound">
<entry key="datacell" type="xstring" value="org.knime.core.data.def.IntCell"/>
<config key="org.knime.core.data.def.IntCell">
<entry key="IntCell" type="xint" value="19"/>
</config>
</config>
</config>
<config key="column_properties"/>
</config>
<config key="column_spec_59">
<entry key="column_name" type="xstring" value="Relative Frequency (preciosubemas20pct que2diasatras)"/>
<config key="element_names">
<entry key="array-size" type="xint" value="0"/>
</config>
<config key="column_type">
<entry key="cell_class" type="xstring" value="org.knime.core.data.def.DoubleCell"/>
</config>
<config key="column_domain">
<config key="lower_bound">
<entry key="datacell" type="xstring" value="org.knime.core.data.def.DoubleCell"/>
<config key="org.knime.core.data.def.DoubleCell">
<entry key="DoubleCell" type="xdouble" value="0.0"/>
</config>
</config>
<config key="upper_bound">
<entry key="datacell" type="xstring" value="org.knime.core.data.def.DoubleCell"/>
<config key="org.knime.core.data.def.DoubleCell">
<entry key="DoubleCell" type="xdouble" value="1.0"/>
</config>
</config>
</config>
<config key="column_properties"/>
</config>
<config key="column_spec_60">
<entry key="column_name" type="xstring" value="TARGET (preciosubemas20pct que2diasatras y estable3velas)"/>
<config key="element_names">
<entry key="array-size" type="xint" value="0"/>
</config>
<config key="column_type">
<entry key="cell_class" type="xstring" value="org.knime.core.data.def.StringCell"/>
</config>
<config key="column_domain">
<config key="possible_values">
<entry key="array-size" type="xint" value="2"/>
<config key="0">
<entry key="datacell" type="xstring" value="org.knime.core.data.def.StringCell"/>
<config key="org.knime.core.data.def.StringCell">
<entry key="StringCell" type="xstring" value="FALSE"/>
</config>
</config>
<config key="1">
<entry key="datacell" type="xstring" value="org.knime.core.data.def.StringCell"/>
<config key="org.knime.core.data.def.StringCell">
<entry key="StringCell" type="xstring" value="TRUE"/>
</config>
</config>
</config>
</config>
<config key="column_properties"/>
</config>
<config key="column_spec_61">
<entry key="column_name" type="xstring" value="TARGET (preciosubemas20pct que2diasatras y estable3velas)_Count"/>
<config key="element_names">
<entry key="array-size" type="xint" value="0"/>
</config>
<config key="column_type">
<entry key="cell_class" type="xstring" value="org.knime.core.data.def.IntCell"/>
</config>
<config key="column_domain">
<config key="lower_bound">
<entry key="datacell" type="xstring" value="org.knime.core.data.def.IntCell"/>
<config key="org.knime.core.data.def.IntCell">
<entry key="IntCell" type="xint" value="3"/>
</config>
</config>
<config key="upper_bound">
<entry key="datacell" type="xstring" value="org.knime.core.data.def.IntCell"/>
<config key="org.knime.core.data.def.IntCell">
<entry key="IntCell" type="xint" value="27"/>
</config>
</config>
</config>
<config key="column_properties"/>
</config>
<config key="column_spec_62">
<entry key="column_name" type="xstring" value="Relative Frequency (TARGET (preciosubemas20pct que2diasatras y estable3velas))"/>
<config key="element_names">
<entry key="array-size" type="xint" value="0"/>
</config>
<config key="column_type">
<entry key="cell_class" type="xstring" value="org.knime.core.data.def.DoubleCell"/>
</config>
<config key="column_domain">
<config key="lower_bound">
<entry key="datacell" type="xstring" value="org.knime.core.data.def.DoubleCell"/>
<config key="org.knime.core.data.def.DoubleCell">
<entry key="DoubleCell" type="xdouble" value="0.0"/>
</config>
</config>
<config key="upper_bound">
<entry key="datacell" type="xstring" value="org.knime.core.data.def.DoubleCell"/>
<config key="org.knime.core.data.def.DoubleCell">
<entry key="DoubleCell" type="xdouble" value="1.0"/>
</config>
</config>
</config>
<config key="column_properties"/>
</config>
</config>
